_find_a_factor.cp312-win_amd64.pyd
FindAFactor/__init__.py
FindAFactor/find_a_factor.py
FindAFactor-6.7.0.dist-info/LICENSE
FindAFactor-6.7.0.dist-info/METADATA
FindAFactor-6.7.0.dist-info/WHEEL
FindAFactor-6.7.0.dist-info/top_level.txt
FindAFactor-6.7.0.dist-info/RECORD
